financial_analyzer_mcp_server/__init__.py
financial_analyzer_mcp_server/license_validator.py
financial_analyzer_mcp_server/main.py
financial_analyzer_mcp_server/server.py
financial_analyzer_mcp_server/tools/__init__.py
financial_analyzer_mcp_server/tools/grizzly_tools.py
financial_analyzer_mcp_server/tools/inflation_tools.py
financial_analyzer_mcp_server/utils/__init__.py
financial_analyzer_mcp_server/utils/financial_calculator.py
financial_analyzer_mcp_server-0.3.2.dist-info/METADATA
financial_analyzer_mcp_server-0.3.2.dist-info/WHEEL
financial_analyzer_mcp_server-0.3.2.dist-info/entry_points.txt
financial_analyzer_mcp_server-0.3.2.dist-info/top_level.txt
financial_analyzer_mcp_server-0.3.2.dist-info/RECORD
