Metadata-Version: 2.4
Name: financial-analyzer-mcp-server
Version: 0.3.2
Summary: MCP server for financial analysis using the 'Cessez de vous faire avoir' method.
Author-email: Ludovic Schoonjans <ludovic@example.com>
License-Expression: MIT
Requires-Python: >=3.12
Requires-Dist: mcp[cli]>=1.14.0
Requires-Dist: pandas>=2.3.2
Requires-Dist: pandas-ta>=0.4.71b0
Requires-Dist: yfinance>=0.2.65
Requires-Dist: matplotlib>=3.8.0
Requires-Dist: requests
